Metadata-Version: 2.1
Name: django-activity-stream-action-expanded
Version: 0.9.1
Summary: Generate generic activity streams from the actions on your site. Users can follow any actors' activities for personalized streams.
Home-page: https://github.com/jalvarezgom/django-activity-stream-action-expanded
Author: Justin Quick
Author-email: justquick@gmail.com
License: BSD 3-Clause
Platform: UNKNOWN
Classifier: Development Status :: 5 - Production/Stable
Classifier: Environment :: Web Environment
Classifier: Framework :: Django
Classifier: Intended Audience :: Developers
Classifier: License :: OSI Approved :: BSD License
Classifier: Operating System :: OS Independent
Classifier: Programming Language :: Python
Classifier: Programming Language :: Python :: 3
Classifier: Topic :: Utilities
Provides-Extra: jsonfield
